{
  "ep_length_mean": [
    29.0
  ],
  "ep_length_mean_T": [
    29
  ],
  "epsilon": [
    1.0
  ],
  "epsilon_T": [
    29
  ],
  "return_mean": [
    {
      "dtype": "float64",
      "py/object": "numpy.float64",
      "value": 43.74776504014444
    }
  ],
  "return_mean_T": [
    29
  ],
  "return_std": [
    {
      "dtype": "float64",
      "py/object": "numpy.float64",
      "value": 0.0
    }
  ],
  "return_std_T": [
    29
  ],
  "test_ep_length_mean": [
    11.0
  ],
  "test_ep_length_mean_T": [
    29
  ],
  "test_return_mean": [
    {
      "dtype": "float64",
      "py/object": "numpy.float64",
      "value": 21.82392723137317
    }
  ],
  "test_return_mean_T": [
    29
  ],
  "test_return_std": [
    {
      "dtype": "float64",
      "py/object": "numpy.float64",
      "value": 20.39529352534272
    }
  ],
  "test_return_std_T": [
    29
  ]
}